wsdflow/__init__.py
wsdflow/multipledimensionscore/__init__.py
wsdflow/multipledimensionscore/core.py
wsdflow/multipledimensionsfun/__init__.py
wsdflow/multipledimensionsfun/fun.py
wsdflow/multipledimensionsfun/run.py
wsdflow/wsdsingledimensionscore/__init__.py
wsdflow/wsdsingledimensionscore/core.py
wsdflow/wsdsingledimensionsfun/__init__.py
wsdflow/wsdsingledimensionsfun/fun.py
wsdflow/wsdsingledimensionsfun/run.py
wsdflow-0.0.2.dist-info/LICENSE
wsdflow-0.0.2.dist-info/METADATA
wsdflow-0.0.2.dist-info/WHEEL
wsdflow-0.0.2.dist-info/top_level.txt
wsdflow-0.0.2.dist-info/RECORD
