Metadata-Version: 2.1
Name: wsdflow
Version: 0.0.2
Summary: This is a mini deep learning framework
Home-page: UNKNOWN
Author: Shida Wei
Author-email: weishida01@163.com
License: UNKNOWN
Platform: UNKNOWN
Classifier: Programming Language :: Python :: 3
Classifier: License :: OSI Approved :: MIT License
Classifier: Operating System :: OS Independent
Requires-Python: >=3.6
